torch_fit/__init__.py
torch_fit-0.0.1.dist-info/LICENSE
torch_fit-0.0.1.dist-info/METADATA
torch_fit-0.0.1.dist-info/WHEEL
torch_fit-0.0.1.dist-info/top_level.txt
torch_fit-0.0.1.dist-info/RECORD
