Metadata-Version: 2.1
Name: torch-fit
Version: 0.0.1
Summary: `Keras.Model.fit`-like torch fit implementation
Home-page: https://github.com/kaelzhang/torch-fit
Author: kaelzhang
Author-email: 
License: MIT
Keywords: torch-fit
Platform: UNKNOWN
Classifier: Topic :: Software Development :: Libraries :: Python Modules
Classifier: Programming Language :: Python :: 3.7
Classifier: Programming Language :: Python :: 3.8
Classifier: Programming Language :: Python :: Implementation :: PyPy
Classifier: Topic :: Software Development :: Libraries :: Python Modules
Classifier: License :: OSI Approved :: MIT License
Requires-Python: >=3.7
Requires-Dist: torch
